odoo/addons/pos_barcode_rule_priced_with_change_rate/README.rst
odoo/addons/pos_barcode_rule_priced_with_change_rate/__init__.py
odoo/addons/pos_barcode_rule_priced_with_change_rate/__manifest__.py
odoo/addons/pos_barcode_rule_priced_with_change_rate/i18n/fr.po
odoo/addons/pos_barcode_rule_priced_with_change_rate/i18n/it.po
odoo/addons/pos_barcode_rule_priced_with_change_rate/i18n/pos_barcode_rule_priced_with_change_rate.pot
odoo/addons/pos_barcode_rule_priced_with_change_rate/models/__init__.py
odoo/addons/pos_barcode_rule_priced_with_change_rate/models/barcode_rule.py
odoo/addons/pos_barcode_rule_priced_with_change_rate/models/pos_config.py
odoo/addons/pos_barcode_rule_priced_with_change_rate/models/res_config_settings.py
odoo/addons/pos_barcode_rule_priced_with_change_rate/readme/CONTRIBUTORS.md
odoo/addons/pos_barcode_rule_priced_with_change_rate/readme/CREDITS.md
odoo/addons/pos_barcode_rule_priced_with_change_rate/readme/DESCRIPTION.md
odoo/addons/pos_barcode_rule_priced_with_change_rate/static/description/icon.png
odoo/addons/pos_barcode_rule_priced_with_change_rate/static/description/index.html
odoo/addons/pos_barcode_rule_priced_with_change_rate/static/src/overrides/components/product_screen/product_screen.esm.js
odoo/addons/pos_barcode_rule_priced_with_change_rate/views/res_config_settings_views.xml
odoo_addon_pos_barcode_rule_priced_with_change_rate-18.0.1.0.0.4.dist-info/METADATA
odoo_addon_pos_barcode_rule_priced_with_change_rate-18.0.1.0.0.4.dist-info/WHEEL
odoo_addon_pos_barcode_rule_priced_with_change_rate-18.0.1.0.0.4.dist-info/top_level.txt
odoo_addon_pos_barcode_rule_priced_with_change_rate-18.0.1.0.0.4.dist-info/RECORD
