Metadata-Version: 2.1
Name: odoo-addon-pos_barcode_rule_priced_with_change_rate
Version: 18.0.1.0.0.4
Requires-Python: >=3.10
Requires-Dist: odoo==18.0.*
Summary: Add a barcode rule to be able to scan a barcode with price encoded (as the standard "Priced Product" rule), and convert the price according to a given change rate.
Home-page: https://github.com/OCA/pos
License: AGPL-3
Author: Odoo Community Association (OCA), Camptocamp
Author-email: support@odoo-community.org
Classifier: Programming Language :: Python
Classifier: Framework :: Odoo
Classifier: Framework :: Odoo :: 18.0
Classifier: License :: OSI Approved :: GNU Affero General Public License v3
